nextroute-1.12.3.dist-info/RECORD
nextroute-1.12.3.dist-info/WHEEL
nextroute-1.12.3.dist-info/top_level.txt
nextroute-1.12.3.dist-info/METADATA
nextroute-1.12.3.dist-info/licenses/LICENSE
tests/solve_golden/__init__.py
tests/solve_golden/main.py
tests/schema/test_input.py
tests/schema/__init__.py
tests/schema/test_output.py
nextroute/options.py
nextroute/version.py
nextroute/__init__.py
nextroute/base_model.py
nextroute/__about__.py
nextroute/solve.py
nextroute/bin/nextroute.exe
nextroute/schema/stop.py
nextroute/schema/vehicle.py
nextroute/schema/__init__.py
nextroute/schema/location.py
nextroute/schema/input.py
nextroute/schema/statistics.py
nextroute/schema/output.py
nextroute/check/__init__.py
nextroute/check/schema.py
