Metadata-Version: 2.4
Name: nextroute
Version: 1.12.3
Summary: Nextroute is an engine for solving Vehicle Routing Problems (VRPs).
Author-email: Nextmv <tech@nextmv.io>
Maintainer-email: Nextmv <tech@nextmv.io>
License: # LICENSE
Project-URL: Homepage, https://www.nextmv.io
Project-URL: Documentation, https://www.nextmv.io/docs/vehicle-routing
Project-URL: Repository, https://github.com/nextmv-io/nextroute
Keywords: decision engineering,decision science,decisions,nextmv,optimization,operations research,solver,vehicle routing problem
Classifier: License :: Other/Proprietary License
Classifier: Operating System :: OS Independent
Classifier: Programming Language :: Python :: 3
Classifier: Programming Language :: Python :: 3.8
Classifier: Programming Language :: Python :: 3.9
Classifier: Programming Language :: Python :: 3.10
Classifier: Programming Language :: Python :: 3.11
Classifier: Programming Language :: Python :: 3.12
Classifier: Programming Language :: Python :: 3.13
Requires-Python: >=3.8
License-File: LICENSE
Requires-Dist: pydantic>=2.5.2
Dynamic: license-file
